lavasnek_rs-0.11.1.dist-info/METADATA
lavasnek_rs-0.11.1.dist-info/WHEEL
lavasnek_rs-0.11.1.dist-info/license_files/LICENSE
lavalink_rs/model/client.pyi
lavalink_rs/model/events.pyi
lavalink_rs/model/http.pyi
lavalink_rs/model/player.pyi
lavalink_rs/model/search.pyi
lavalink_rs/model/track.pyi
lavalink_rs/model/__init__.pyi
lavalink_rs/py.typed
lavalink_rs/__init__.py
lavalink_rs/__init__.pyi
lavalink_rs/lavalink_rs.cp311-win32.pyd
lavasnek_rs-0.11.1.dist-info/RECORD
