Metadata-Version: 2.1
Name: lavasnek-rs
Version: 0.11.1
License-File: LICENSE
Summary: Lavalink API wrapper for discord audio playing
Keywords: lavalink,discord,serenity,twilight,songbird
Home-Page: https://gitlab.com/vicky5124/lavalink-rs/
Author: vicky5124 <vickyf5124@gmail.com>
Author-email: vicky5124 <vickyf5124@gmail.com>
License: MPL-2.0
Requires-Python: >=3.8, <3.13
Project-URL: Source Code, https://gitlab.com/vicky5124/lavalink-rs/
